llama_index/py.typed
llama_index/vector_stores/openGauss/__init__.py
llama_index/vector_stores/openGauss/base.py
llama_index_vector_stores_opengauss-0.2.1.dist-info/METADATA
llama_index_vector_stores_opengauss-0.2.1.dist-info/WHEEL
llama_index_vector_stores_opengauss-0.2.1.dist-info/licenses/LICENSE
llama_index_vector_stores_opengauss-0.2.1.dist-info/RECORD
