Metadata-Version: 2.4
Name: llama-index-vector-stores-opengauss
Version: 0.2.1
Summary: llama-index vector_stores openGauss integration
Author-email: Your Name <you@example.com>
License-Expression: MIT
License-File: LICENSE
Requires-Python: <3.13,>=3.9
Requires-Dist: llama-index-core<0.15,>=0.13.0
Requires-Dist: llama-index-vector-stores-postgres<0.7.0,>=0.6.0
Requires-Dist: opengauss-sqlalchemy>=2.4.0
